{
    "initial_state": "S0",
    "final_states" : {
            "IDT" : "IDENTIFIER_LOOKUP",
            "ART" : "ARITHMETIC_OPERATOR",
            "REL_F" : "RELATIONAL_OPERATOR",
            "ASG_F" : "ASSIGN_OPERATOR",
            "NUM" : "NUMBER",
            "NUM_D_F" : "NUMBER",
            "NUM_D_E_F" : "NUMBER",
            "NUM_D_E_NEG_F" : "NUMBER",
            "CHR_F" : "CHAR_LITERAL",
            "STR_F" : "STRING_LITERAL",
            "COM" : "COMMA",
            "SEM" : "SEMICOLON",
            "COL" : "COLON",
            "DOT" : "DOT",
            "LPA" : "LPARENTHESIS",
            "RPA" : "RPARANTHESIS",
            "LBR" : "LBRACKET",
            "RBR" : "RBRACKET",
            "RANGE" : "RANGE_OPERATOR"
    },
    "transition" : {
        "S0" : {
            "A" : "IDT",
            "B" : "IDT",
            "C" : "IDT",
            "D" : "IDT",
            "E" : "IDT",
            "F" : "IDT",
            "G" : "IDT",
            "H" : "IDT",
            "I" : "IDT",
            "J" : "IDT",
            "L" : "IDT",
            "M" : "IDT",
            "N" : "IDT",
            "O" : "IDT",
            "P" : "IDT",
            "Q" : "IDT",
            "R" : "IDT",
            "S" : "IDT",
            "T" : "IDT",
            "U" : "IDT",
            "V" : "IDT",
            "W" : "IDT",
            "X" : "IDT",
            "Y" : "IDT",
            "a" : "IDT",
            "b" : "IDT",
            "c" : "IDT",
            "d" : "IDT",
            "e" : "IDT",
            "f" : "IDT",
            "g" : "IDT",
            "h" : "IDT",
            "i" : "IDT",
            "j" : "IDT",
            "k" : "IDT",
            "l" : "IDT",
            "m" : "IDT",
            "n" : "IDT",
            "o" : "IDT",
            "p" : "IDT",
            "q" : "IDT",
            "r" : "IDT",
            "s" : "IDT",
            "t" : "IDT",
            "u" : "IDT",
            "v" : "IDT",
            "w" : "IDT",
            "x" : "IDT",
            "y" : "IDT",
            "z" : "IDT",
            "0" : "NUM",
            "1" : "NUM",
            "2" : "NUM",
            "3" : "NUM",
            "4" : "NUM",
            "5" : "NUM",
            "6" : "NUM",
            "7" : "NUM",
            "8" : "NUM",
            "9" : "NUM",
            "+" : "ART",
            "*" : "ART",
            "-" : "MIN",
            "/" : "ART",
            "=" : "REL_F",
            "<" : "REL_S",
            ">" : "REL_B",
            ";" : "SEM",
            "," : "COM",
            "." : "DOT",
            "(" : "LPA",
            ")" : "RPA",
            "[" : "LBR",
            "]" : "RBR",
            "'" : "CHR",
            ":" : "COL_ASG"
        },
        "IDT" : {
            "A" : "IDT",
            "B" : "IDT",
            "C" : "IDT",
            "D" : "IDT",
            "E" : "IDT",
            "F" : "IDT",
            "G" : "IDT",
            "H" : "IDT",
            "I" : "IDT",
            "J" : "IDT",
            "L" : "IDT",
            "M" : "IDT",
            "N" : "IDT",
            "O" : "IDT",
            "P" : "IDT",
            "Q" : "IDT",
            "R" : "IDT",
            "S" : "IDT",
            "T" : "IDT",
            "U" : "IDT",
            "V" : "IDT",
            "W" : "IDT",
            "X" : "IDT",
            "Y" : "IDT",
            "a" : "IDT",
            "b" : "IDT",
            "c" : "IDT",
            "d" : "IDT",
            "e" : "IDT",
            "f" : "IDT",
            "g" : "IDT",
            "h" : "IDT",
            "i" : "IDT",
            "j" : "IDT",
            "k" : "IDT",
            "l" : "IDT",
            "m" : "IDT",
            "n" : "IDT",
            "o" : "IDT",
            "p" : "IDT",
            "q" : "IDT",
            "r" : "IDT",
            "s" : "IDT",
            "t" : "IDT",
            "u" : "IDT",
            "v" : "IDT",
            "w" : "IDT",
            "x" : "IDT",
            "y" : "IDT",
            "z" : "IDT",
            "0" : "IDT",
            "1" : "IDT",
            "2" : "IDT",
            "3" : "IDT",
            "4" : "IDT",
            "5" : "IDT",
            "6" : "IDT",
            "7" : "IDT",
            "8" : "IDT",
            "9" : "IDT",
            "_" : "IDT" 
        },
        "NUM" : {
            "0" : "NUM",
            "1" : "NUM",
            "2" : "NUM",
            "3" : "NUM",
            "4" : "NUM",
            "5" : "NUM",
            "6" : "NUM",
            "7" : "NUM",
            "8" : "NUM",
            "9" : "NUM",
            "." : "NUM_D"
        }, 
        "NUM_D" : {
            "E" : "NUM_D_E",
            "0" : "NUM_D_F",
            "1" : "NUM_D_F",
            "2" : "NUM_D_F",
            "3" : "NUM_D_F",
            "4" : "NUM_D_F",
            "5" : "NUM_D_F",
            "6" : "NUM_D_F",
            "7" : "NUM_D_F",
            "8" : "NUM_D_F",
            "9" : "NUM_D_F"
        },
        "NUM_D_F" : {
            "E" : "NUM_D_E",
            "0" : "NUM_D_F",
            "1" : "NUM_D_F",
            "2" : "NUM_D_F",
            "3" : "NUM_D_F",
            "4" : "NUM_D_F",
            "5" : "NUM_D_F",
            "6" : "NUM_D_F",
            "7" : "NUM_D_F",
            "8" : "NUM_D_F",
            "9" : "NUM_D_F"
        },
        "NUM_D_E" : {
            "-" : "NUM_D_E_NEG",
            "0" : "NUM_D_E_F",
            "1" : "NUM_D_E_F",
            "2" : "NUM_D_E_F",
            "3" : "NUM_D_E_F",
            "4" : "NUM_D_E_F",
            "5" : "NUM_D_E_F",
            "6" : "NUM_D_E_F",
            "7" : "NUM_D_E_F",
            "8" : "NUM_D_E_F",
            "9" : "NUM_D_E_F"
        },
        "NUM_D_E_F" : {
            "-" : "NUM_D_E_NEG",
            "0" : "NUM_D_E_F",
            "1" : "NUM_D_E_F",
            "2" : "NUM_D_E_F",
            "3" : "NUM_D_E_F",
            "4" : "NUM_D_E_F",
            "5" : "NUM_D_E_F",
            "6" : "NUM_D_E_F",
            "7" : "NUM_D_E_F",
            "8" : "NUM_D_E_F",
            "9" : "NUM_D_E_F"
        },
        "NUM_D_E_NEG" : {
            "0" : "NUM_D_E",
            "1" : "NUM_D_E",
            "2" : "NUM_D_E",
            "3" : "NUM_D_E",
            "4" : "NUM_D_E",
            "5" : "NUM_D_E",
            "6" : "NUM_D_E",
            "7" : "NUM_D_E",
            "8" : "NUM_D_E",
            "9" : "NUM_D_E"
        },
        "NUM_D_E_NEG_F" : {
            "0" : "NUM_D_E_NEG_F",
            "1" : "NUM_D_E_NEG_F",
            "2" : "NUM_D_E_NEG_F",
            "3" : "NUM_D_E_NEG_F",
            "4" : "NUM_D_E_NEG_F",
            "5" : "NUM_D_E_NEG_F",
            "6" : "NUM_D_E_NEG_F",
            "7" : "NUM_D_E_NEG_F",
            "8" : "NUM_D_E_NEG_F",
            "9" : "NUM_D_E_NEG_F"
        },
        "MIN" : {
            " " : "ART",
            "0" : "NUM",
            "1" : "NUM",
            "2" : "NUM",
            "3" : "NUM",
            "4" : "NUM",
            "5" : "NUM",
            "6" : "NUM",
            "7" : "NUM",
            "8" : "NUM",
            "9" : "NUM"
        },
        "REL_S" : {
            ">" : "REL_F",
            "=" : "REL_F"
        },
        "REL_B" : {
            "=" : "REL_F"
        },
        "COL_ASG" : {
            "\n" : "COL",
            "=" : "ASG_F",
            " " : "COL" 
        }, 
        "CHR" : {
            "ANY" : "CHR_1",
            "'" : "CHR_F"
        },
        "CHR_1" : {
            "ANY" : "STR",
            "'" : "CHR_F"
        },
        "STR" : {
            "ANY" : "STR",
            "'" : "STR_F"
        },
        "DOT" : {
            "." : "RANGE"
        }
    }
}
